hive/__init__.py
hive/core.py
hive/mqtt.py
hive/msgpack.py
hive/protobuf.py
hive/queen.py
hive/redis.py
hive/ros.py
hive/stomp.py
hive_py-0.0.7.dist-info/LICENSE
hive_py-0.0.7.dist-info/METADATA
hive_py-0.0.7.dist-info/WHEEL
hive_py-0.0.7.dist-info/top_level.txt
hive_py-0.0.7.dist-info/RECORD
